{
  "items": [
    {
      "id": "los-gatos-2026-06-02-0a5a9dd8",
      "cityId": "los-gatos",
      "cityName": "Los Gatos",
      "date": "2026-06-02",
      "headline": "Los Gatos to hold municipal election on November 3, 2026",
      "summary": "City Council adopted a resolution calling a general municipal election for Tuesday, November 3, 2026, to fill three council seats.",
      "sourceUrl": "https://losgatos-ca.municodemeetings.com/",
      "source": "council"
    },
    {
      "id": "los-gatos-2026-06-02-8647e60c",
      "cityId": "los-gatos",
      "cityName": "Los Gatos",
      "date": "2026-06-02",
      "headline": "Final map approved for Tract 10675 Boulevard development",
      "summary": "City Council approved the final subdivision map for Tract 10675 Boulevard, clearing the way for the project to proceed to construction.",
      "sourceUrl": "https://losgatos-ca.municodemeetings.com/",
      "source": "council"
    },
    {
      "id": "san-jose-2026-05-27-b42b0deb",
      "cityId": "san-jose",
      "cityName": "San José",
      "date": "2026-05-27",
      "headline": "$1.3M commercial project permitted on South 10th Street",
      "summary": "A commercial/industrial building received a permit at 1935 S 10th St. The project's scale and location in an industrial corridor could affect traffic and land use in that area.",
      "sourceUrl": "https://sjpermits.org/",
      "source": "permit"
    },
    {
      "id": "san-jose-2026-05-27-7530837d",
      "cityId": "san-jose",
      "cityName": "San José",
      "date": "2026-05-27",
      "headline": "Semiconductor equipment installation permitted at North 1st Street",
      "summary": "Intermolecular received a $600,000 permit for a chlorine trifluoride gas cabinet installation at 3011 N 1st St, indicating continued advanced manufacturing activity in San José's tech corridor.",
      "sourceUrl": "https://sjpermits.org/",
      "source": "permit"
    },
    {
      "id": "mountain-view-2026-05-26-713833ae",
      "cityId": "mountain-view",
      "cityName": "Mountain View",
      "date": "2026-05-26",
      "headline": "Parks and Recreation Strategic Plan Adopted",
      "summary": "City Council adopted a new strategic plan for parks and recreation. The plan sets direction for how Mountain View will manage and develop its parks and recreation services.",
      "sourceUrl": "https://mountainview.legistar.com/Calendar.aspx?From=5%2F26%2F2026&To=5%2F26%2F2026",
      "source": "council"
    },
    {
      "id": "mountain-view-2026-05-26-5d7dcf38",
      "cityId": "mountain-view",
      "cityName": "Mountain View",
      "date": "2026-05-26",
      "headline": "City Decarbonization Five-Year Plan to be Presented",
      "summary": "Council will hear a study session on Mountain View's decarbonization goal and a proposed five-year plan with specific approach and actions to reduce emissions.",
      "sourceUrl": "https://mountainview.legistar.com/Calendar.aspx?From=5%2F26%2F2026&To=5%2F26%2F2026",
      "source": "council"
    },
    {
      "id": "santa-clara-2026-05-26-b36c528c",
      "cityId": "santa-clara",
      "cityName": "Santa Clara",
      "date": "2026-05-26",
      "headline": "City to spend $1.6M on highway patrol traffic management for World Cup",
      "summary": "Santa Clara City Council and Stadium Authority approved a standard agreement with the California Highway Patrol for traffic management services during FIFA World Cup events, with a projected cost of $1.6 million and related budget amendment.",
      "sourceUrl": "https://santaclara.legistar.com/Calendar.aspx?From=5%2F26%2F2026&To=5%2F26%2F2026",
      "source": "council"
    },
    {
      "id": "campbell-2026-05-26-6f5f93d6",
      "cityId": "campbell",
      "cityName": "Campbell",
      "date": "2026-05-26",
      "headline": "Planning Commission to review East Campbell Avenue line project",
      "summary": "The Planning Commission will hear a presentation on a draft East Campbell Avenue line project. The meeting will also cover the capital improvement plan for citywide projects to ensure alignment with the Campbell 2040 general plan.",
      "sourceUrl": "https://www.campbellca.gov/AgendaCenter/City-Council-10",
      "source": "planning"
    }
  ],
  "generatedAt": "2026-06-02T19:10:42.461Z"
}
