{
  "items": [
    {
      "id": "cupertino-2026-07-21-cd7ab4d3",
      "cityId": "cupertino",
      "cityName": "Cupertino",
      "date": "2026-07-21",
      "headline": "Council to discuss three lawsuits against Cupertino in closed session",
      "summary": "The council is scheduled to meet in closed session with legal counsel on pending litigation, including cases brought by Lixin (Leon) Chen and others, by Yes in My Backyard, and by the Garden Gate Coalition for Mary Avenue Safety, all filed in Santa Clara County Superior Court.",
      "sourceUrl": "https://cupertino.legistar.com/Calendar.aspx?From=7%2F21%2F2026&To=7%2F21%2F2026",
      "source": "council"
    },
    {
      "id": "san-jose-2026-07-20-2b6ba953",
      "cityId": "san-jose",
      "cityName": "San José",
      "date": "2026-07-20",
      "headline": "City legalizes existing garage-to-ADU conversion under amnesty program",
      "summary": "A permit at 952 Harliss Av retroactively legalizes a detached garage that was already converted to an ADU, using the city's code amnesty process rather than authorizing new construction.",
      "sourceUrl": "https://sjpermits.org/",
      "source": "permit"
    },
    {
      "id": "san-jose-2026-07-17-b6e5c324",
      "cityId": "san-jose",
      "cityName": "San José",
      "date": "2026-07-17",
      "headline": "Three ADUs permitted at one Lewis Road multi-family lot",
      "summary": "Two permits issued for detached ADUs at 458 Lewis Rd (#5 and #6), with #6 covering 2 units, adding three accessory units to a single multi-family property—more ADU density on one lot than typically seen in these filings.",
      "sourceUrl": "https://sjpermits.org/",
      "source": "permit"
    }
  ],
  "generatedAt": "2026-07-23T03:11:20.379Z"
}
