{
  "_meta": {
    "generatedAt": "2026-05-01T23:17:21.571Z",
    "generator": "generate-reddit-pulse",
    "sourceCount": 16,
    "sources": [
      "r/SanJose",
      "r/siliconvalley",
      "r/PaloAlto",
      "r/MountainView",
      "r/Sunnyvale",
      "r/SantaClara",
      "r/Cupertino",
      "r/Saratoga_CA",
      "r/losgatos",
      "r/Milpitas",
      "r/campbell",
      "r/bayarea",
      "r/AskSF",
      "r/bayareafood",
      "r/SanJoseSharks",
      "r/sjearthquakes"
    ]
  },
  "posts": [
    {
      "id": "1t18pq1",
      "sub": "SanJose",
      "title": "saw these Wasian meetup flyers walking around north beach LOL",
      "displayTitle": "Saw these Wasian meetup flyers walking around North Beach LOL",
      "summary": "Spotted Wasian meetup flyers in North Beach area.",
      "category": "discussion",
      "topic": "bay-area-community-meetups",
      "image": "https://x92cgaghviaolmmg.public.blob.vercel-storage.com/reddit-pulse/1t18pq1.png",
      "score": 0,
      "numComments": 3,
      "ageHours": 0.2,
      "createdUtc": 1777676245,
      "permalink": "https://www.reddit.com/r/SanJose/comments/1t18pq1/saw_these_wasian_meetup_flyers_walking_around/",
      "externalUrl": "https://www.reddit.com/gallery/1t18osp"
    },
    {
      "id": "1t18cib",
      "sub": "SanJose",
      "title": "Howdy fellow anglers…",
      "displayTitle": "Howdy fellow anglers…",
      "summary": "Seeking fishing gear retailers and affordable licensing in San Jose.",
      "category": "discussion",
      "topic": "san-jose-fishing-supplies",
      "image": "https://x92cgaghviaolmmg.public.blob.vercel-storage.com/reddit-pulse/1t18cib.png",
      "score": 1,
      "numComments": 5,
      "ageHours": 0.5,
      "createdUtc": 1777675311,
      "permalink": "https://www.reddit.com/r/SanJose/comments/1t18cib/howdy_fellow_anglers/",
      "externalUrl": null
    },
    {
      "id": "1t16ebx",
      "sub": "bayarea",
      "title": "Any traditional Palestinian clothing Shops in the bay ?",
      "displayTitle": "Any traditional Palestinian clothing shops in the Bay?",
      "summary": "Seeking traditional Palestinian Renaissance faire clothing recommendations.",
      "category": "discussion",
      "topic": "renaissance-faire-clothing",
      "image": "https://x92cgaghviaolmmg.public.blob.vercel-storage.com/reddit-pulse/1t16ebx.png",
      "score": 43,
      "numComments": 15,
      "ageHours": 1.8,
      "createdUtc": 1777670566,
      "permalink": "https://www.reddit.com/r/bayarea/comments/1t16ebx/any_traditional_palestinian_clothing_shops_in_the/",
      "externalUrl": "https://www.reddit.com/gallery/1t16ebx"
    },
    {
      "id": "1t16dvo",
      "sub": "Sunnyvale",
      "title": "Current Best Men's Haircut Spots In And Around Sunnyvale?",
      "displayTitle": "Current best men's haircut spots in and around Sunnyvale?",
      "summary": "Seeking affordable men's haircut recommendations in Sunnyvale.",
      "category": "discussion",
      "topic": "sunnyvale-barbershop",
      "image": "https://x92cgaghviaolmmg.public.blob.vercel-storage.com/reddit-pulse/1t16dvo.png",
      "score": 2,
      "numComments": 5,
      "ageHours": 1.8,
      "createdUtc": 1777670534,
      "permalink": "https://www.reddit.com/r/Sunnyvale/comments/1t16dvo/current_best_mens_haircut_spots_in_and_around/",
      "externalUrl": null
    },
    {
      "id": "1t15ioj",
      "sub": "SanJose",
      "title": "Pit bull needs adopting before May 4th 5 PM",
      "displayTitle": "Pit bull needs adopting before May 4th 5 PM",
      "summary": "Pit bull in San Jose shelter needs adoption before May 4th deadline.",
      "category": "discussion",
      "topic": "san-jose-pet-adoption",
      "image": "https://x92cgaghviaolmmg.public.blob.vercel-storage.com/reddit-pulse/1t15ioj.png",
      "score": 10,
      "numComments": 9,
      "ageHours": 2.4,
      "createdUtc": 1777668551,
      "permalink": "https://www.reddit.com/r/SanJose/comments/1t15ioj/pit_bull_needs_adopting_before_may_4th_5_pm/",
      "externalUrl": "https://24petconnect.com/SNJSAllPets/Details/SNJS/A1400556"
    },
    {
      "id": "1t13lq3",
      "sub": "mountainview",
      "title": "What data is this device collecting?",
      "displayTitle": "What data is this device collecting?",
      "summary": "Question about mystery data-collecting devices on Mountain View streets.",
      "category": "discussion",
      "topic": "mountain-view-autonomous-vehicles",
      "image": "https://x92cgaghviaolmmg.public.blob.vercel-storage.com/reddit-pulse/1t13lq3.png",
      "score": 11,
      "numComments": 10,
      "ageHours": 3.6,
      "createdUtc": 1777664267,
      "permalink": "https://www.reddit.com/r/mountainview/comments/1t13lq3/what_data_is_this_device_collecting/",
      "externalUrl": "https://i.redd.it/r964rtfjwkyg1.jpeg"
    },
    {
      "id": "1t130oq",
      "sub": "bayarea",
      "title": "Valley Link rail project faces delays, rising costs as Altamont Pass commute worsens",
      "displayTitle": "Valley Link rail project faces delays, rising costs as Altamont Pass commute worsens",
      "summary": "Valley Link rail project faces delays and rising costs amid commute struggles.",
      "category": "news",
      "topic": "valley-link-rail-project",
      "image": "https://x92cgaghviaolmmg.public.blob.vercel-storage.com/reddit-pulse/1t130oq.png",
      "score": 15,
      "numComments": 8,
      "ageHours": 3.9,
      "createdUtc": 1777662979,
      "permalink": "https://www.reddit.com/r/bayarea/comments/1t130oq/valley_link_rail_project_faces_delays_rising/",
      "externalUrl": "https://www.eastbaytimes.com/2026/04/30/valley-link-was-supposed-to-ease-brutal-commutes-now-its-smaller-pricier-and-still-years-away/"
    },
    {
      "id": "1t12o3w",
      "sub": "bayarea",
      "title": "Pregnancy friendly day spas",
      "displayTitle": "Pregnancy friendly day spas",
      "summary": "Seeking pregnancy-friendly day spas with prenatal massage in Bay Area.",
      "category": "discussion",
      "topic": "bay-area-prenatal-spa",
      "image": "https://x92cgaghviaolmmg.public.blob.vercel-storage.com/reddit-pulse/1t12o3w.png",
      "score": 8,
      "numComments": 14,
      "ageHours": 4.2,
      "createdUtc": 1777662208,
      "permalink": "https://www.reddit.com/r/bayarea/comments/1t12o3w/pregnancy_friendly_day_spas/",
      "externalUrl": null
    },
    {
      "id": "1t0m83m",
      "sub": "Sunnyvale",
      "title": "Wtf is this light?",
      "displayTitle": "WTF is this light?",
      "summary": "Question about mysterious light sighting near Sunnyvale.",
      "category": "discussion",
      "topic": "sunnyvale-mysterious-light",
      "image": "https://x92cgaghviaolmmg.public.blob.vercel-storage.com/reddit-pulse/1t0m83m.png",
      "score": 17,
      "numComments": 12,
      "ageHours": 15.9,
      "createdUtc": 1777619902,
      "permalink": "https://www.reddit.com/r/Sunnyvale/comments/1t0m83m/wtf_is_this_light/",
      "externalUrl": "https://i.redd.it/uw4nh2cm8hyg1.jpeg"
    },
    {
      "id": "1t0l2ai",
      "sub": "Cupertino",
      "title": "Helicopter flying around",
      "displayTitle": "Helicopter flying around",
      "summary": "Question about late-night helicopter activity near Apple campus.",
      "category": "discussion",
      "topic": "cupertino-helicopter-activity",
      "image": "https://x92cgaghviaolmmg.public.blob.vercel-storage.com/reddit-pulse/1t0l2ai.png",
      "score": 8,
      "numComments": 4,
      "ageHours": 17,
      "createdUtc": 1777615998,
      "permalink": "https://www.reddit.com/r/Cupertino/comments/1t0l2ai/helicopter_flying_around/",
      "externalUrl": null
    },
    {
      "id": "1t0kcc0",
      "sub": "Campbell",
      "title": "Devil Wears Prada2 at Pruneyard!! Such a fun movie❤️",
      "displayTitle": "Devil Wears Prada 2 at Pruneyard!! Such a fun movie❤️",
      "summary": "Devil Wears Prada 2 screening at Campbell's Pruneyard shopping center.",
      "category": "event",
      "topic": "pruneyard-movie-night",
      "image": "https://x92cgaghviaolmmg.public.blob.vercel-storage.com/reddit-pulse/1t0kcc0.png",
      "score": 27,
      "numComments": 2,
      "ageHours": 17.6,
      "createdUtc": 1777613673,
      "permalink": "https://www.reddit.com/r/Campbell/comments/1t0kcc0/devil_wears_prada2_at_pruneyard_such_a_fun_movie/",
      "externalUrl": "https://i.redd.it/vpgecjp3qgyg1.jpeg"
    },
    {
      "id": "1t0jhe2",
      "sub": "santaclara",
      "title": "New to Santa clara - looking for fun, chaotic, yapper friends",
      "displayTitle": "New to Santa Clara - looking for fun, chaotic, yapper friends",
      "summary": "New grad student in Santa Clara seeking fun, outgoing friends for internship.",
      "category": "discussion",
      "topic": "santa-clara-newcomer-social",
      "image": "https://x92cgaghviaolmmg.public.blob.vercel-storage.com/reddit-pulse/1t0jhe2.png",
      "score": 0,
      "numComments": 7,
      "ageHours": 18.4,
      "createdUtc": 1777611041,
      "permalink": "https://www.reddit.com/r/santaclara/comments/1t0jhe2/new_to_santa_clara_looking_for_fun_chaotic_yapper/",
      "externalUrl": null
    }
  ]
}
