{
  "_meta": {
    "generatedAt": "2026-06-01T23:16:49.570Z",
    "generator": "generate-reddit-pulse",
    "sourceCount": 16,
    "sources": [
      "r/SanJose",
      "r/siliconvalley",
      "r/PaloAlto",
      "r/MountainView",
      "r/Sunnyvale",
      "r/SantaClara",
      "r/Cupertino",
      "r/Saratoga_CA",
      "r/losgatos",
      "r/Milpitas",
      "r/campbell",
      "r/bayarea",
      "r/AskSF",
      "r/bayareafood",
      "r/SanJoseSharks",
      "r/sjearthquakes"
    ]
  },
  "posts": [
    {
      "id": "1tu83ap",
      "sub": "bayarea",
      "title": "Review - Kathmandu Cuisine Los Altos",
      "displayTitle": "Review - Kathmandu Cuisine Los Altos",
      "summary": "High school newspaper reviews Kathmandu Cuisine in Los Altos with positive recommendations.",
      "category": "restaurant_news",
      "topic": "local-restaurant-reviews",
      "image": "https://x92cgaghviaolmmg.public.blob.vercel-storage.com/reddit-pulse/1tu83ap.png",
      "score": 0,
      "numComments": 0,
      "ageHours": 0.7,
      "createdUtc": 1780352988,
      "permalink": "https://www.reddit.com/r/bayarea/comments/1tu83ap/review_kathmandu_cuisine_los_altos/",
      "externalUrl": null
    },
    {
      "id": "1tu7364",
      "sub": "bayarea",
      "title": "Are there any hotels here that accept housebroken dogs to stay with their human?",
      "displayTitle": "Are there any hotels here that accept housebroken dogs to stay with their human?",
      "summary": "San Jose resident seeks pet-friendly hotel accommodation during home fumigation.",
      "category": "discussion",
      "topic": "pet-friendly-hotels-bay-area",
      "image": "https://x92cgaghviaolmmg.public.blob.vercel-storage.com/reddit-pulse/1tu7364.png",
      "score": 0,
      "numComments": 0,
      "ageHours": 1.3,
      "createdUtc": 1780350761,
      "permalink": "https://www.reddit.com/r/bayarea/comments/1tu7364/are_there_any_hotels_here_that_accept_housebroken/",
      "externalUrl": null
    },
    {
      "id": "1tu6yu4",
      "sub": "SanJose",
      "title": "Any watch parties or events for FIFA?",
      "displayTitle": "Any watch parties or events for FIFA?",
      "summary": "Local seeking FIFA watch party venues and events in San Jose.",
      "category": "discussion",
      "topic": "san-jose-fifa-watch-parties",
      "image": "https://x92cgaghviaolmmg.public.blob.vercel-storage.com/reddit-pulse/1tu6yu4.png",
      "score": 0,
      "numComments": 0,
      "ageHours": 1.4,
      "createdUtc": 1780350498,
      "permalink": "https://www.reddit.com/r/SanJose/comments/1tu6yu4/any_watch_parties_or_events_for_fifa/",
      "externalUrl": null
    },
    {
      "id": "1tu53f1",
      "sub": "SanJose",
      "title": "Lost wallet Home Depot",
      "displayTitle": "Lost wallet Home Depot",
      "summary": "Person who found cash-filled wallet at Home Depot seeking to return it to owner.",
      "category": "discussion",
      "topic": "san-jose-lost-found-kindness",
      "image": "https://x92cgaghviaolmmg.public.blob.vercel-storage.com/reddit-pulse/1tu53f1.png",
      "score": 0,
      "numComments": 0,
      "ageHours": 2.5,
      "createdUtc": 1780346450,
      "permalink": "https://www.reddit.com/r/SanJose/comments/1tu53f1/lost_wallet_home_depot/",
      "externalUrl": null
    },
    {
      "id": "1tu4xyl",
      "sub": "SanJose",
      "title": "Soccer for 4year old",
      "displayTitle": "Soccer for 4 year old",
      "summary": "Parent seeking summer soccer enrollment for 4-year-old.",
      "category": "discussion",
      "topic": "san-jose-youth-soccer-programs",
      "image": "https://x92cgaghviaolmmg.public.blob.vercel-storage.com/reddit-pulse/1tu4xyl.png",
      "score": 0,
      "numComments": 0,
      "ageHours": 2.6,
      "createdUtc": 1780346131,
      "permalink": "https://www.reddit.com/r/SanJose/comments/1tu4xyl/soccer_for_4year_old/",
      "externalUrl": null
    },
    {
      "id": "1tu4fla",
      "sub": "SantaClara",
      "title": "What do you actually check before signing a lease in Santa Clara?",
      "displayTitle": "What do you actually check before signing a lease in Santa Clara?",
      "summary": "Santa Clara resident seeks advice on what to check before signing apartment lease after past bad experience.",
      "category": "discussion",
      "topic": "apartment-rental-tips-santa-clara",
      "image": "https://x92cgaghviaolmmg.public.blob.vercel-storage.com/reddit-pulse/1tu4fla.png",
      "score": 0,
      "numComments": 0,
      "ageHours": 2.9,
      "createdUtc": 1780345096,
      "permalink": "https://www.reddit.com/r/santaclara/comments/1tu4fla/what_do_you_actually_check_before_signing_a_lease/",
      "externalUrl": null
    },
    {
      "id": "1tu49en",
      "sub": "PaloAlto",
      "title": "Outstanding in the Field - 6/13",
      "displayTitle": "Outstanding in the Field - 6/13",
      "summary": "Selling one ticket to sold-out Outstanding in the Field farm dinner at Hidden Villa.",
      "category": "event",
      "topic": "outstanding-in-the-field-event",
      "image": "https://x92cgaghviaolmmg.public.blob.vercel-storage.com/reddit-pulse/1tu49en.png",
      "score": 0,
      "numComments": 0,
      "ageHours": 3,
      "createdUtc": 1780344742,
      "permalink": "https://www.reddit.com/r/paloalto/comments/1tu49en/outstanding_in_the_field_613/",
      "externalUrl": null
    },
    {
      "id": "1tu1fzv",
      "sub": "AskSF",
      "title": "Did I horribly overpay for a World Cup ticket (Austria vs Jordan @ Santa Clara) ? Seat - Zone 1 Row 10 (side view)",
      "displayTitle": "Did I horribly overpay for a World Cup ticket (Austria vs Jordan @ Santa Clara)? Seat - Zone 1 Row 10 (side view)",
      "summary": "Asking if World Cup ticket price for Austria vs Jordan in Santa Clara was overpaid.",
      "category": "discussion",
      "topic": "world-cup-ticket-advice-santa-clara",
      "image": "https://x92cgaghviaolmmg.public.blob.vercel-storage.com/reddit-pulse/1tu1fzv.png",
      "score": 0,
      "numComments": 0,
      "ageHours": 4.6,
      "createdUtc": 1780339011,
      "permalink": "https://www.reddit.com/r/AskSF/comments/1tu1fzv/did_i_horribly_overpay_for_a_world_cup_ticket/",
      "externalUrl": null
    },
    {
      "id": "1tu0aiy",
      "sub": "Sunnyvale",
      "title": "Iso cat sitter",
      "displayTitle": "ISO cat sitter",
      "summary": "Looking for reliable cat sitter for two cats during frequent travel.",
      "category": "discussion",
      "topic": "sunnyvale-pet-sitting-services",
      "image": "https://x92cgaghviaolmmg.public.blob.vercel-storage.com/reddit-pulse/1tu0aiy.png",
      "score": 0,
      "numComments": 0,
      "ageHours": 5.2,
      "createdUtc": 1780336832,
      "permalink": "https://www.reddit.com/r/Sunnyvale/comments/1tu0aiy/iso_cat_sitter/",
      "externalUrl": null
    },
    {
      "id": "1ttz7z0",
      "sub": "bayarea",
      "title": "What does comfortable, rich, or wealthy mean here",
      "displayTitle": "What does comfortable, rich, or wealthy mean here",
      "summary": "Exploring definitions of comfortable, rich, and wealthy among tech workers.",
      "category": "discussion",
      "topic": "silicon-valley-wealth-discussion",
      "image": "https://x92cgaghviaolmmg.public.blob.vercel-storage.com/reddit-pulse/1ttz7z0.png",
      "score": 0,
      "numComments": 0,
      "ageHours": 5.8,
      "createdUtc": 1780334734,
      "permalink": "https://www.reddit.com/r/bayarea/comments/1ttz7z0/what_does_comfortable_rich_or_wealthy_mean_here/",
      "externalUrl": null
    },
    {
      "id": "1ttxxzn",
      "sub": "Cupertino",
      "title": "Finally they found a replacement for Merlion Restaurant",
      "displayTitle": "Finally they found a replacement for Merlion Restaurant",
      "summary": "Cupertino restaurant community celebrates new establishment replacing beloved Merlion.",
      "category": "restaurant_news",
      "topic": "cupertino-restaurant-openings",
      "image": "https://x92cgaghviaolmmg.public.blob.vercel-storage.com/reddit-pulse/1ttxxzn.png",
      "score": 0,
      "numComments": 0,
      "ageHours": 6.5,
      "createdUtc": 1780332204,
      "permalink": "https://www.reddit.com/r/Cupertino/comments/1ttxxzn/finally_they_found_a_replacement_for_merlion/",
      "externalUrl": null
    },
    {
      "id": "1ttxelb",
      "sub": "sjearthquakes",
      "title": "San Jose Earthquakes, CEFCU Announce Goals for Education Community Grant Program to Support Local School Communities",
      "displayTitle": "San Jose Earthquakes, CEFCU Announce Goals for Education Community Grant Program to Support Local School Communities",
      "summary": "San Jose Earthquakes and CEFCU announce education community grant program for local schools.",
      "category": "news",
      "topic": "san-jose-earthquakes-community",
      "image": "https://x92cgaghviaolmmg.public.blob.vercel-storage.com/reddit-pulse/1ttxelb.png",
      "score": 0,
      "numComments": 0,
      "ageHours": 6.8,
      "createdUtc": 1780331106,
      "permalink": "https://www.reddit.com/r/SJEarthquakes/comments/1ttxelb/san_jose_earthquakes_cefcu_announce_goals_for/",
      "externalUrl": null
    }
  ]
}
