{
  "_meta": {
    "generatedAt": "2026-04-25T23:22:22.956Z",
    "generator": "generate-reddit-pulse",
    "sourceCount": 16,
    "sources": [
      "r/SanJose",
      "r/siliconvalley",
      "r/PaloAlto",
      "r/MountainView",
      "r/Sunnyvale",
      "r/SantaClara",
      "r/Cupertino",
      "r/Saratoga_CA",
      "r/losgatos",
      "r/Milpitas",
      "r/campbell",
      "r/bayarea",
      "r/AskSF",
      "r/bayareafood",
      "r/SanJoseSharks",
      "r/sjearthquakes"
    ]
  },
  "posts": [
    {
      "id": "1svpwr7",
      "sub": "SanJose",
      "title": "Went to lake Cunningham park & haven’t been in years. Took me an hour to walk the entire park. So many different plants and animals.",
      "displayTitle": "Went to Lake Cunningham Park & haven't been in years. Took me an hour to walk the entire park. So many different plants and animals.",
      "summary": "Visitor rediscovers Lake Cunningham Park and praises diverse wildlife.",
      "category": "discussion",
      "topic": "san-jose-parks",
      "image": "https://x92cgaghviaolmmg.public.blob.vercel-storage.com/reddit-pulse/1svpwr7.png",
      "score": 18,
      "numComments": 3,
      "ageHours": 0.9,
      "createdUtc": 1777156024,
      "permalink": "https://www.reddit.com/r/SanJose/comments/1svpwr7/went_to_lake_cunningham_park_havent_been_in_years/",
      "externalUrl": "https://www.reddit.com/gallery/1svpwr7"
    },
    {
      "id": "1svprc3",
      "sub": "SanJoseSharks",
      "title": "In Game Production",
      "displayTitle": "In Game Production",
      "summary": "Fan impressed by in-game production quality at Barracuda arena.",
      "category": "sports",
      "topic": "sharks-barracuda-ahl",
      "image": "https://x92cgaghviaolmmg.public.blob.vercel-storage.com/reddit-pulse/1svprc3.png",
      "score": 9,
      "numComments": 3,
      "ageHours": 1,
      "createdUtc": 1777155636,
      "permalink": "https://www.reddit.com/r/SanJoseSharks/comments/1svprc3/in_game_production/",
      "externalUrl": null
    },
    {
      "id": "1svo2yi",
      "sub": "bayarea",
      "title": "Want to Spring Clean Your Bookshelf? Where to Sell or Donate Used Books in the Bay Area",
      "displayTitle": "Want to Spring Clean Your Bookshelf? Where to Sell or Donate Used Books in the Bay Area",
      "summary": "Guide for where to sell or donate used books in Bay Area.",
      "category": "discussion",
      "topic": "book-selling-donating",
      "image": "https://x92cgaghviaolmmg.public.blob.vercel-storage.com/reddit-pulse/1svo2yi.png",
      "score": 13,
      "numComments": 3,
      "ageHours": 2.1,
      "createdUtc": 1777151458,
      "permalink": "https://www.reddit.com/r/bayarea/comments/1svo2yi/want_to_spring_clean_your_bookshelf_where_to_sell/",
      "externalUrl": "https://www.kqed.org/news/12080674/want-to-spring-clean-your-bookshelf-where-to-sell-or-donate-used-books-in-the-bay-area"
    },
    {
      "id": "1svm7jc",
      "sub": "SanJose",
      "title": "Thoughts on Bill’s Cafe?",
      "displayTitle": "Thoughts on Bill's Cafe?",
      "summary": "Community discussion about Bill's Cafe history and lore.",
      "category": "discussion",
      "topic": "san-jose-diners",
      "image": "https://x92cgaghviaolmmg.public.blob.vercel-storage.com/reddit-pulse/1svm7jc.png",
      "score": 22,
      "numComments": 74,
      "ageHours": 3.3,
      "createdUtc": 1777147076,
      "permalink": "https://www.reddit.com/r/SanJose/comments/1svm7jc/thoughts_on_bills_cafe/",
      "externalUrl": null
    },
    {
      "id": "1svklhy",
      "sub": "SanJose",
      "title": "South Bay Alcohol-Free Women's Hangouts - May & June 2026!",
      "displayTitle": "South Bay Alcohol-Free Women's Hangouts - May & June 2026!",
      "summary": "Alcohol-free women's hangout events organized for May and June in South Bay.",
      "category": "event",
      "topic": "san-jose-social-events",
      "image": "https://x92cgaghviaolmmg.public.blob.vercel-storage.com/reddit-pulse/1svklhy.png",
      "score": 24,
      "numComments": 0,
      "ageHours": 4.4,
      "createdUtc": 1777143387,
      "permalink": "https://www.reddit.com/r/SanJose/comments/1svklhy/south_bay_alcoholfree_womens_hangouts_may_june/",
      "externalUrl": "https://i.redd.it/3j8ecqrgvdxg1.png"
    },
    {
      "id": "1svivd3",
      "sub": "bayarea",
      "title": "The bay is beautiful",
      "displayTitle": "The bay is beautiful",
      "summary": "Visitor from Minnesota praises Bay Area as most beautiful region visited.",
      "category": "discussion",
      "topic": "bay-area-appreciation",
      "image": "https://x92cgaghviaolmmg.public.blob.vercel-storage.com/reddit-pulse/1svivd3.png",
      "score": 183,
      "numComments": 8,
      "ageHours": 5.5,
      "createdUtc": 1777139450,
      "permalink": "https://www.reddit.com/r/bayarea/comments/1svivd3/the_bay_is_beautiful/",
      "externalUrl": "https://www.reddit.com/gallery/1svivd3"
    },
    {
      "id": "1svisd7",
      "sub": "Sunnyvale",
      "title": "Murphy Association Community event at Murphy Park, Sunnyvale today/Saturday- April 25th",
      "displayTitle": "Murphy Association Community event at Murphy Park, Sunnyvale today/Saturday - April 25th",
      "summary": "Murphy Association community event at Murphy Park Saturday with books and snacks.",
      "category": "event",
      "topic": "sunnyvale-community-events",
      "image": "https://x92cgaghviaolmmg.public.blob.vercel-storage.com/reddit-pulse/1svisd7.png",
      "score": 31,
      "numComments": 4,
      "ageHours": 5.5,
      "createdUtc": 1777139260,
      "permalink": "https://www.reddit.com/r/Sunnyvale/comments/1svisd7/murphy_association_community_event_at_murphy_park/",
      "externalUrl": "https://www.reddit.com/gallery/1svisd7"
    },
    {
      "id": "1svhz5n",
      "sub": "Campbell",
      "title": "Dough Zone signage!",
      "displayTitle": "Dough Zone signage!",
      "summary": "Dough Zone signage spotted indicating upcoming location opening in Campbell.",
      "category": "restaurant_news",
      "topic": "campbell-restaurants",
      "image": "https://x92cgaghviaolmmg.public.blob.vercel-storage.com/reddit-pulse/1svhz5n.png",
      "score": 26,
      "numComments": 8,
      "ageHours": 6.1,
      "createdUtc": 1777137371,
      "permalink": "https://www.reddit.com/r/Campbell/comments/1svhz5n/dough_zone_signage/",
      "externalUrl": "https://i.redd.it/jaksjt8tddxg1.jpeg"
    },
    {
      "id": "1svh063",
      "sub": "bayarea",
      "title": "Kukje Bakery, from legacy Bay Area Korean grocery, opens in Daly City",
      "displayTitle": "Kukje Bakery, from legacy Bay Area Korean grocery, opens in Daly City",
      "summary": "Kukje Bakery from legacy Bay Area Korean grocery opens in Daly City.",
      "category": "restaurant_news",
      "topic": "bay-area-korean-bakery",
      "image": "https://x92cgaghviaolmmg.public.blob.vercel-storage.com/reddit-pulse/1svh063.png",
      "score": 13,
      "numComments": 0,
      "ageHours": 6.7,
      "createdUtc": 1777135115,
      "permalink": "https://www.reddit.com/r/bayarea/comments/1svh063/kukje_bakery_from_legacy_bay_area_korean_grocery/",
      "externalUrl": "https://www.sfchronicle.com/food/restaurants/article/kukje-bakery-daly-city-22224211.php"
    },
    {
      "id": "1sv2l59",
      "sub": "SanJoseSharks",
      "title": "Favorite sharks game from the 2025-2026 season?",
      "displayTitle": "Favorite Sharks game from the 2025-2026 season?",
      "summary": "Sharks fan discusses favorite games from recent 2025-2026 season.",
      "category": "sports",
      "topic": "sharks-season-review",
      "image": "https://x92cgaghviaolmmg.public.blob.vercel-storage.com/reddit-pulse/1sv2l59.png",
      "score": 40,
      "numComments": 55,
      "ageHours": 18.5,
      "createdUtc": 1777092662,
      "permalink": "https://www.reddit.com/r/SanJoseSharks/comments/1sv2l59/favorite_sharks_game_from_the_20252026_season/",
      "externalUrl": null
    },
    {
      "id": "1sv0pr4",
      "sub": "mountainview",
      "title": "When MV launch their Universal Basic Income Pilot, should they have focused on low-income artists rather than random low-income lottery?",
      "displayTitle": "When MV launches their Universal Basic Income Pilot, should they have focused on low-income artists rather than random low-income lottery?",
      "summary": "Community discusses focus of Mountain View Universal Basic Income pilot.",
      "category": "discussion",
      "topic": "mountain-view-ubi-policy",
      "image": "https://x92cgaghviaolmmg.public.blob.vercel-storage.com/reddit-pulse/1sv0pr4.png",
      "score": 0,
      "numComments": 10,
      "ageHours": 20,
      "createdUtc": 1777087113,
      "permalink": "https://www.reddit.com/r/mountainview/comments/1sv0pr4/when_mv_launch_their_universal_basic_income_pilot/",
      "externalUrl": "https://www.reddit.com/gallery/1sv0pr4"
    },
    {
      "id": "1sun0w1",
      "sub": "mountainview",
      "title": "I lived in Mountain View, CA for seven years. I don't anymore, but here's a mountain drawing I made this week from a photo I took on Oahu years ago",
      "displayTitle": "I lived in Mountain View, CA for seven years. I don't anymore, but here's a mountain drawing I made this week from a photo I took on Oahu years ago",
      "summary": "Mountain View resident shares landscape drawing reflecting time in the area.",
      "category": "discussion",
      "topic": "mountain-view-community",
      "image": "https://x92cgaghviaolmmg.public.blob.vercel-storage.com/reddit-pulse/1sun0w1.png",
      "score": 56,
      "numComments": 17,
      "ageHours": 29.4,
      "createdUtc": 1777053210,
      "permalink": "https://www.reddit.com/r/mountainview/comments/1sun0w1/i_lived_in_mountain_view_ca_for_seven_years_i/",
      "externalUrl": "https://i.redd.it/czgpee5kf6xg1.jpeg"
    }
  ]
}
