{
  "_meta": {
    "description": "Venues/orgs we tried to tag but couldn't find in social-handles.json. Auto-populated at gen time. Resolve by adding entries to social-handles.json (this file's entries are then dropped on next run).",
    "lastUpdated": "2026-05-02"
  },
  "gaps": {
    "central park library edinger room": {
      "displayName": "Central Park Library - Edinger Room",
      "firstSeen": "2026-05-02",
      "occurrences": 2,
      "contexts": [
        {
          "slot": "tonight-pick",
          "kind": "venue"
        }
      ],
      "lastSeen": "2026-05-02"
    },
    "teen library leaders": {
      "displayName": "Teen Library Leaders",
      "firstSeen": "2026-05-02",
      "occurrences": 2,
      "contexts": [
        {
          "slot": "tonight-pick",
          "kind": "title"
        }
      ],
      "lastSeen": "2026-05-02"
    },
    "cantor arts center": {
      "displayName": "Cantor Arts Center",
      "firstSeen": "2026-05-02",
      "occurrences": 4,
      "contexts": [
        {
          "slot": "day-plan",
          "city": "palo-alto",
          "category": "museum",
          "kind": "card"
        }
      ],
      "lastSeen": "2026-05-02"
    },
    "homeridge park": {
      "displayName": "Homeridge Park",
      "firstSeen": "2026-05-02",
      "occurrences": 1,
      "contexts": [
        {
          "slot": "day-plan",
          "city": "santa-clara",
          "category": "outdoor",
          "kind": "card"
        }
      ],
      "lastSeen": "2026-05-02"
    },
    "sandy wool lake gazebo": {
      "displayName": "Sandy Wool Lake - Gazebo",
      "firstSeen": "2026-05-02",
      "occurrences": 1,
      "contexts": [
        {
          "slot": "day-plan",
          "city": "milpitas",
          "category": "outdoor",
          "kind": "card"
        }
      ],
      "lastSeen": "2026-05-02"
    },
    "cafe nur": {
      "displayName": "Cafe Nur",
      "firstSeen": "2026-05-02",
      "occurrences": 1,
      "contexts": [
        {
          "slot": "day-plan",
          "city": "los-altos",
          "category": "food",
          "kind": "card"
        }
      ],
      "lastSeen": "2026-05-02"
    },
    "asian american stories award ceremony 2026": {
      "displayName": "Asian American Stories Award Ceremony 2026",
      "firstSeen": "2026-05-02",
      "occurrences": 1,
      "contexts": [
        {
          "slot": "day-plan",
          "city": "santa-clara",
          "category": "arts",
          "kind": "card"
        }
      ],
      "lastSeen": "2026-05-02"
    },
    "xiang xiang noodle": {
      "displayName": "Xiang Xiang Noodle",
      "firstSeen": "2026-05-02",
      "occurrences": 1,
      "contexts": [
        {
          "slot": "day-plan",
          "city": "sunnyvale",
          "category": "food",
          "kind": "card"
        }
      ],
      "lastSeen": "2026-05-02"
    },
    "braly park": {
      "displayName": "Braly Park",
      "firstSeen": "2026-05-02",
      "occurrences": 1,
      "contexts": [
        {
          "slot": "day-plan",
          "city": "sunnyvale",
          "category": "outdoor",
          "kind": "card"
        }
      ],
      "lastSeen": "2026-05-02"
    },
    "art of science 2026": {
      "displayName": "Art of Science 2026",
      "firstSeen": "2026-05-02",
      "occurrences": 1,
      "contexts": [
        {
          "slot": "day-plan",
          "city": "palo-alto",
          "category": "arts",
          "kind": "card"
        }
      ],
      "lastSeen": "2026-05-02"
    },
    "stevens canyon trail": {
      "displayName": "Stevens Canyon Trail",
      "firstSeen": "2026-05-02",
      "occurrences": 1,
      "contexts": [
        {
          "slot": "day-plan",
          "city": "cupertino",
          "category": "outdoor",
          "kind": "card"
        }
      ],
      "lastSeen": "2026-05-02"
    },
    "rio adobe southwest cafe": {
      "displayName": "Rio Adobe Southwest Cafe",
      "firstSeen": "2026-05-02",
      "occurrences": 1,
      "contexts": [
        {
          "slot": "day-plan",
          "city": "cupertino",
          "category": "food",
          "kind": "card"
        }
      ],
      "lastSeen": "2026-05-02"
    },
    "san jose municipal rose garden": {
      "displayName": "San Jose Municipal Rose Garden",
      "firstSeen": "2026-05-02",
      "occurrences": 1,
      "contexts": [
        {
          "slot": "day-plan",
          "city": "san-jose",
          "category": "outdoor",
          "kind": "card"
        }
      ],
      "lastSeen": "2026-05-02"
    },
    "blackberry farm golf course": {
      "displayName": "Blackberry Farm Golf Course",
      "firstSeen": "2026-05-02",
      "occurrences": 2,
      "contexts": [
        {
          "slot": "day-plan",
          "city": "cupertino",
          "category": "entertainment",
          "kind": "card"
        }
      ],
      "lastSeen": "2026-05-02"
    },
    "creative break": {
      "displayName": "Creative Break",
      "firstSeen": "2026-05-02",
      "occurrences": 1,
      "contexts": [
        {
          "slot": "day-plan",
          "city": "los-gatos",
          "category": "events",
          "kind": "card"
        }
      ],
      "lastSeen": "2026-05-02"
    },
    "black mountain trail": {
      "displayName": "Black Mountain Trail",
      "firstSeen": "2026-05-02",
      "occurrences": 1,
      "contexts": [
        {
          "slot": "day-plan",
          "city": "los-altos",
          "category": "outdoor",
          "kind": "card"
        }
      ],
      "lastSeen": "2026-05-02"
    },
    "mountain view sports pavilion": {
      "displayName": "Mountain View Sports Pavilion",
      "firstSeen": "2026-05-02",
      "occurrences": 1,
      "contexts": [
        {
          "slot": "day-plan",
          "city": "mountain-view",
          "category": "entertainment",
          "kind": "card"
        }
      ],
      "lastSeen": "2026-05-02"
    },
    "playground": {
      "displayName": "Playground",
      "firstSeen": "2026-05-02",
      "occurrences": 1,
      "contexts": [
        {
          "slot": "day-plan",
          "city": "santa-clara",
          "category": "outdoor",
          "kind": "card"
        }
      ],
      "lastSeen": "2026-05-02"
    }
  }
}
