{
  "generatedAt": "2026-04-22T11:06:09.451Z",
  "meetings": {
    "san-jose": {
      "date": "2026-04-28",
      "displayDate": "Tue, Apr 28",
      "bodyName": "City Council",
      "location": "Council Chambers",
      "url": "https://sanjose.legistar.com/MeetingDetail.aspx?ID=7619&GUID=D3114273-D33D-4410-B969-8C809CDBB3A9",
      "legistarEventId": 7619,
      "agendaItems": [
        {
          "title": "Police Staffing, Expenditures, and Workload Audit Report.",
          "sequence": 50
        },
        {
          "title": "Spring 2026 Intergovernmental Relations Report.",
          "sequence": 51
        },
        {
          "title": "Amendments to City Council Policy 1-16, Policy for the Issuance of Multifamily Housing Revenue Bonds.",
          "sequence": 52
        },
        {
          "title": "Park Master Plan and Official Name for a Future Park Located on Rinconada Drive.",
          "sequence": 57
        },
        {
          "title": "H23-040, T23-027 & ER23-251 - Site Development Permit and Vesting Tentative Map for Certain Real Property Located at Camden Avenue and Singletree Way.",
          "sequence": 66
        }
      ]
    },
    "campbell": {
      "date": "2026-05-05",
      "displayDate": "Tue, May 5",
      "bodyName": "City Council",
      "location": null,
      "url": "https://www.campbellca.gov/AgendaCenter/City-Council-10",
      "agendaItems": []
    },
    "saratoga": {
      "date": "2026-05-06",
      "displayDate": "Wed, May 6",
      "bodyName": "City Council",
      "location": null,
      "url": "https://www.saratoga.ca.us/AgendaCenter/City-Council-13",
      "agendaItems": []
    },
    "los-altos": {
      "date": "2026-04-28",
      "displayDate": "Tue, Apr 28",
      "bodyName": "City Council",
      "location": null,
      "url": "https://www.losaltosca.gov/AgendaCenter/City-Council-4",
      "agendaItems": []
    },
    "milpitas": {
      "date": "2026-05-05",
      "displayDate": "Tue, May 5",
      "bodyName": "City Council",
      "location": "455 E. Calaveras Blvd, Milpitas",
      "url": "https://www.milpitas.gov/129/Agendas-Minutes",
      "agendaItems": []
    },
    "los-gatos": {
      "date": "2026-05-05",
      "displayDate": "Tue, May 5",
      "bodyName": "Town Council",
      "location": null,
      "url": "https://losgatos-ca.municodemeetings.com/",
      "agendaItems": []
    }
  }
}
