{
  "weekendLabel": "April 17 – April 19",
  "weekendStart": "2026-04-17",
  "weekendEnd": "2026-04-19",
  "generatedAt": "2026-04-17T23:13:47.222Z",
  "picks": [
    {
      "id": "sjda-148a490fcdd22fde",
      "title": "420 in the Park featuring The Legendary Wailers & Baby Bash",
      "date": "2026-04-18",
      "displayDate": "Sat, Apr 18",
      "time": null,
      "endTime": "11:59 PM",
      "city": "san-jose",
      "venue": "Plaza de Cesar Chavez",
      "cost": "paid",
      "url": "https://sjdowntown.com/event/420-in-the-park/",
      "category": "family",
      "why": "420 in the Park brings The Legendary Wailers and Baby Bash to Plaza de Cesar Chavez for a rare outdoor music festival."
    },
    {
      "id": "paloalto-69964e9681b67dfe32a745cc",
      "title": "Palo Alto Earth Day Festival",
      "date": "2026-04-19",
      "displayDate": "Sun, Apr 19",
      "time": "1:00 PM",
      "endTime": "4:00 PM",
      "city": "palo-alto",
      "venue": "Palo Alto City Library",
      "cost": "free",
      "url": "https://paloalto.bibliocommons.com/events/69964e9681b67dfe32a745cc",
      "category": "family",
      "why": "Palo Alto Earth Day Festival offers free family fun celebrating sustainability with local vendors and interactive activities."
    },
    {
      "id": "inbound-0d2f6d771b610543",
      "title": "Viva CalleSJ: East Side Quest",
      "date": "2026-04-19",
      "displayDate": "Sun, Apr 19",
      "time": "10:00 AM",
      "endTime": "3:00 PM",
      "city": "san-jose",
      "venue": "White Road and Alum Rock Avenue",
      "cost": null,
      "url": "https://vivacallesj.org/",
      "category": "arts",
      "why": "Viva CalleSJ closes miles of East San José streets for walking, biking, and skating—a vibrant community celebration you can't do any other weekend."
    }
  ]
}
